<?xml version="1.0" encoding="UTF-8"?>
<!DOCTYPE mapper PUBLIC "-//mybatis.org//DTD Mapper 3.0//EN" "http://mybatis.org/dtd/mybatis-3-mapper.dtd">
<mapper namespace="com.cardif.satelite.telemarketing.dao.TlmkBaseRPMapper">
	<resultMap id="BaseResultMap" type="com.cardif.satelite.model.TlmkBaseRP">
		<!-- WARNING - @mbggenerated This element is automatically generated by MyBatis Generator, do not modify. This element was generated on Wed Jan 22 12:45:18 
			COT 2014. -->
		<id column="PK" jdbcType="NUMERIC" property="pk" />
		<result column="COD_BASE" jdbcType="NUMERIC" property="codBase" />
		<result column="SECUENCIA_TLMK" jdbcType="NVARCHAR" property="secuenciaTlmk" />
		<result column="TARGET" jdbcType="NVARCHAR" property="target" />
		<result column="FUE_MAX" jdbcType="NVARCHAR" property="fueMax" />
		<result column="MARCA1" jdbcType="NVARCHAR" property="marca1" />
		<result column="DOCIDE_ENL" jdbcType="NVARCHAR" property="docideEnl" />
		<result column="TIPDOC" jdbcType="NVARCHAR" property="tipdoc" />
		<result column="TIP_TARJETA" jdbcType="NVARCHAR" property="tipTarjeta" />
		<result column="RANGO_UTILIZACION" jdbcType="NVARCHAR" property="rangoUtilizacion" />
		<result column="RANGO_LINEA_RIPLEY" jdbcType="NVARCHAR" property="rangoLineaRipley" />
		<result column="RANGO_SALDOS_RIPLEY" jdbcType="NVARCHAR" property="rangoSaldosRipley" />
		<result column="RANGO_ANTIGUEDAD" jdbcType="NVARCHAR" property="rangoAntiguedad" />
		<result column="RECENCIA_TO" jdbcType="NVARCHAR" property="recenciaTo" />
		<result column="FECHA_ACT" jdbcType="TIMESTAMP" property="fechaAct" />
		<result column="FECHA_VENCIMIENTO" jdbcType="TIMESTAMP" property="fechaVencimiento" />
		<result column="FECHA_EMBOZADO" jdbcType="TIMESTAMP" property="fechaEmbozado" />
		<result column="SEXO" jdbcType="NVARCHAR" property="sexo" />
		<result column="EDAD" jdbcType="NVARCHAR" property="edad" />
		<result column="NSE" jdbcType="NVARCHAR" property="nse" />
		<result column="NOMBRESYAPELLIDOS" jdbcType="NVARCHAR" property="nombresyapellidos" />
		<result column="OCUPACION" jdbcType="NVARCHAR" property="ocupacion" />
		<result column="DIRECCION" jdbcType="NVARCHAR" property="direccion" />
		<result column="DISTRITO" jdbcType="NVARCHAR" property="distrito" />
		<result column="DEPARTAMENTO" jdbcType="NVARCHAR" property="departamento" />
		<result column="FONO_EMPLEADOR_1" jdbcType="NVARCHAR" property="fonoEmpleador1" />
		<result column="FONO_CLIENTE_1" jdbcType="NVARCHAR" property="fonoCliente1" />
		<result column="FONO_CLIENTE_2" jdbcType="NVARCHAR" property="fonoCliente2" />
		<result column="CELULAR_0" jdbcType="NVARCHAR" property="celular0" />
		<result column="CELULAR_1" jdbcType="NVARCHAR" property="celular1" />
		<result column="OFICINA" jdbcType="NVARCHAR" property="oficina" />
		<result column="CASA" jdbcType="NVARCHAR" property="casa" />
		<result column="CEL1" jdbcType="NVARCHAR" property="cel1" />
		<result column="CEL2" jdbcType="NVARCHAR" property="cel2" />
		<result column="CEL3" jdbcType="NVARCHAR" property="cel3" />
		<result column="CEL4" jdbcType="NVARCHAR" property="cel4" />
		<result column="CEL5" jdbcType="NVARCHAR" property="cel5" />
		<result column="ESTADO" jdbcType="NVARCHAR" property="estado" />
		<result column="DES_MENSAJE" jdbcType="NVARCHAR" property="desMensaje" />
	</resultMap>
	<sql id="Example_Where_Clause">
		<!-- WARNING - @mbggenerated This element is automatically generated by MyBatis Generator, do not modify. This element was generated on Wed Jan 22 12:45:18 
			COT 2014. -->
		<where>
			<foreach collection="oredCriteria" item="criteria" separator="or">
				<if test="criteria.valid">
					<trim prefix="(" prefixOverrides="and" suffix=")">
						<foreach collection="criteria.criteria" item="criterion">
							<choose>
								<when test="criterion.noValue">
									and ${criterion.condition}
								</when>
								<when test="criterion.singleValue">
									and ${criterion.condition} #{criterion.value}
								</when>
								<when test="criterion.betweenValue">
									and ${criterion.condition} #{criterion.value} and #{criterion.secondValue}
								</when>
								<when test="criterion.listValue">
									and ${criterion.condition}
									<foreach close=")" collection="criterion.value" item="listItem" open="(" separator=",">
										#{listItem}
									</foreach>
								</when>
							</choose>
						</foreach>
					</trim>
				</if>
			</foreach>
		</where>
	</sql>
	<sql id="Update_By_Example_Where_Clause">
		<!-- WARNING - @mbggenerated This element is automatically generated by MyBatis Generator, do not modify. This element was generated on Wed Jan 22 12:45:18 
			COT 2014. -->
		<where>
			<foreach collection="example.oredCriteria" item="criteria" separator="or">
				<if test="criteria.valid">
					<trim prefix="(" prefixOverrides="and" suffix=")">
						<foreach collection="criteria.criteria" item="criterion">
							<choose>
								<when test="criterion.noValue">
									and ${criterion.condition}
								</when>
								<when test="criterion.singleValue">
									and ${criterion.condition} #{criterion.value}
								</when>
								<when test="criterion.betweenValue">
									and ${criterion.condition} #{criterion.value} and #{criterion.secondValue}
								</when>
								<when test="criterion.listValue">
									and ${criterion.condition}
									<foreach close=")" collection="criterion.value" item="listItem" open="(" separator=",">
										#{listItem}
									</foreach>
								</when>
							</choose>
						</foreach>
					</trim>
				</if>
			</foreach>
		</where>
	</sql>
	<sql id="Base_Column_List">
		<!-- WARNING - @mbggenerated This element is automatically generated by MyBatis Generator, do not modify. This element was generated on Wed Jan 22 12:45:18 
			COT 2014. -->
		PK, COD_BASE, SECUENCIA_TLMK, TARGET, FUE_MAX, MARCA1, DOCIDE_ENL, TIPDOC, TIP_TARJETA,
		RANGO_UTILIZACION, RANGO_LINEA_RIPLEY, RANGO_SALDOS_RIPLEY,
		RANGO_ANTIGUEDAD, RECENCIA_TO,
		FECHA_ACT, FECHA_VENCIMIENTO, FECHA_EMBOZADO, SEXO, EDAD, NSE, NOMBRESYAPELLIDOS,
		OCUPACION, DIRECCION, DISTRITO,
		DEPARTAMENTO, FONO_EMPLEADOR_1, FONO_CLIENTE_1, FONO_CLIENTE_2,
		CELULAR_0, CELULAR_1, OFICINA, CASA, CEL1, CEL2, CEL3, CEL4, CEL5, ESTADO,
		DES_MENSAJE
	</sql>
	<select id="selectByExample" parameterType="com.cardif.satelite.model.TlmkBaseRPExample" resultMap="BaseResultMap">
		<!-- WARNING - @mbggenerated This element is automatically generated by MyBatis Generator, do not modify. This element was generated on Wed Jan 22 12:45:18 
			COT 2014. -->
		select
		<if test="distinct">
			distinct
		</if>
		<include refid="Base_Column_List" />
		from dbo.TLMK_BASE_RP
		<if test="_parameter != null">
			<include refid="Example_Where_Clause" />
		</if>
		<if test="orderByClause != null">
			order by ${orderByClause}
		</if>
	</select>
	<select id="selectByPrimaryKey" parameterType="java.lang.Long" resultMap="BaseResultMap">
		<!-- WARNING - @mbggenerated This element is automatically generated by MyBatis Generator, do not modify. This element was generated on Wed Jan 22 12:45:18 
			COT 2014. -->
		select
		<include refid="Base_Column_List" />
		from dbo.TLMK_BASE_RP
		where PK = #{pk,jdbcType=NUMERIC}
	</select>
	<delete id="deleteByPrimaryKey" parameterType="java.lang.Long">
		<!-- WARNING - @mbggenerated This element is automatically generated by MyBatis Generator, do not modify. This element was generated on Wed Jan 22 12:45:18 
			COT 2014. -->
		delete from dbo.TLMK_BASE_RP
		where PK = #{pk,jdbcType=NUMERIC}
	</delete>
	<delete id="deleteByExample" parameterType="com.cardif.satelite.model.TlmkBaseRPExample">
		<!-- WARNING - @mbggenerated This element is automatically generated by MyBatis Generator, do not modify. This element was generated on Wed Jan 22 12:45:18 
			COT 2014. -->
		delete from dbo.TLMK_BASE_RP
		<if test="_parameter != null">
			<include refid="Example_Where_Clause" />
		</if>
	</delete>
	<insert id="insert" parameterType="com.cardif.satelite.model.TlmkBaseRP">
		<!-- WARNING - @mbggenerated This element is automatically generated by MyBatis Generator, do not modify. This element was generated on Wed Jan 22 12:45:18 
			COT 2014. -->
		<selectKey keyProperty="pk" order="AFTER" resultType="java.lang.Long">
			SELECT SCOPE_IDENTITY()
		</selectKey>
		insert into dbo.TLMK_BASE_RP (COD_BASE, SECUENCIA_TLMK, TARGET,
		FUE_MAX, MARCA1, DOCIDE_ENL,
		TIPDOC, TIP_TARJETA, RANGO_UTILIZACION,
		RANGO_LINEA_RIPLEY, RANGO_SALDOS_RIPLEY,
		RANGO_ANTIGUEDAD, RECENCIA_TO, FECHA_ACT,
		FECHA_VENCIMIENTO, FECHA_EMBOZADO, SEXO,
		EDAD, NSE,
		NOMBRESYAPELLIDOS,
		OCUPACION, DIRECCION, DISTRITO,
		DEPARTAMENTO, FONO_EMPLEADOR_1, FONO_CLIENTE_1,
		FONO_CLIENTE_2, CELULAR_0, CELULAR_1,
		OFICINA, CASA,
		CEL1,
		CEL2, CEL3, CEL4,
		CEL5, ESTADO, DES_MENSAJE
		)
		values (#{codBase,jdbcType=NUMERIC}, #{secuenciaTlmk,jdbcType=NVARCHAR},
		#{target,jdbcType=NVARCHAR},
		#{fueMax,jdbcType=NVARCHAR}, #{marca1,jdbcType=NVARCHAR}, #{docideEnl,jdbcType=NVARCHAR},
		#{tipdoc,jdbcType=NVARCHAR},
		#{tipTarjeta,jdbcType=NVARCHAR}, #{rangoUtilizacion,jdbcType=NVARCHAR},
		#{rangoLineaRipley,jdbcType=NVARCHAR},
		#{rangoSaldosRipley,jdbcType=NVARCHAR},
		#{rangoAntiguedad,jdbcType=NVARCHAR}, #{recenciaTo,jdbcType=NVARCHAR}, #{fechaAct,jdbcType=TIMESTAMP},
		#{fechaVencimiento,jdbcType=TIMESTAMP}, #{fechaEmbozado,jdbcType=TIMESTAMP}, #{sexo,jdbcType=NVARCHAR},
		#{edad,jdbcType=NVARCHAR},
		#{nse,jdbcType=NVARCHAR}, #{nombresyapellidos,jdbcType=NVARCHAR},
		#{ocupacion,jdbcType=NVARCHAR}, #{direccion,jdbcType=NVARCHAR},
		#{distrito,jdbcType=NVARCHAR},
		#{departamento,jdbcType=NVARCHAR}, #{fonoEmpleador1,jdbcType=NVARCHAR}, #{fonoCliente1,jdbcType=NVARCHAR},
		#{fonoCliente2,jdbcType=NVARCHAR}, #{celular0,jdbcType=NVARCHAR}, #{celular1,jdbcType=NVARCHAR},
		#{oficina,jdbcType=NVARCHAR},
		#{casa,jdbcType=NVARCHAR}, #{cel1,jdbcType=NVARCHAR},
		#{cel2,jdbcType=NVARCHAR}, #{cel3,jdbcType=NVARCHAR}, #{cel4,jdbcType=NVARCHAR},
		#{cel5,jdbcType=NVARCHAR}, #{estado,jdbcType=NVARCHAR}, #{desMensaje,jdbcType=NVARCHAR}
		)
	</insert>
	<insert id="insertSelective" parameterType="com.cardif.satelite.model.TlmkBaseRP">
		<!-- WARNING - @mbggenerated This element is automatically generated by MyBatis Generator, do not modify. This element was generated on Wed Jan 22 12:45:18 
			COT 2014. -->
		<selectKey keyProperty="pk" order="AFTER" resultType="java.lang.Long">
			SELECT SCOPE_IDENTITY()
		</selectKey>
		insert into dbo.TLMK_BASE_RP
		<trim prefix="(" suffix=")" suffixOverrides=",">
			<if test="codBase != null">
				COD_BASE,
			</if>
			<if test="secuenciaTlmk != null">
				SECUENCIA_TLMK,
			</if>
			<if test="target != null">
				TARGET,
			</if>
			<if test="fueMax != null">
				FUE_MAX,
			</if>
			<if test="marca1 != null">
				MARCA1,
			</if>
			<if test="docideEnl != null">
				DOCIDE_ENL,
			</if>
			<if test="tipdoc != null">
				TIPDOC,
			</if>
			<if test="tipTarjeta != null">
				TIP_TARJETA,
			</if>
			<if test="rangoUtilizacion != null">
				RANGO_UTILIZACION,
			</if>
			<if test="rangoLineaRipley != null">
				RANGO_LINEA_RIPLEY,
			</if>
			<if test="rangoSaldosRipley != null">
				RANGO_SALDOS_RIPLEY,
			</if>
			<if test="rangoAntiguedad != null">
				RANGO_ANTIGUEDAD,
			</if>
			<if test="recenciaTo != null">
				RECENCIA_TO,
			</if>
			<if test="fechaAct != null">
				FECHA_ACT,
			</if>
			<if test="fechaVencimiento != null">
				FECHA_VENCIMIENTO,
			</if>
			<if test="fechaEmbozado != null">
				FECHA_EMBOZADO,
			</if>
			<if test="sexo != null">
				SEXO,
			</if>
			<if test="edad != null">
				EDAD,
			</if>
			<if test="nse != null">
				NSE,
			</if>
			<if test="nombresyapellidos != null">
				NOMBRESYAPELLIDOS,
			</if>
			<if test="ocupacion != null">
				OCUPACION,
			</if>
			<if test="direccion != null">
				DIRECCION,
			</if>
			<if test="distrito != null">
				DISTRITO,
			</if>
			<if test="departamento != null">
				DEPARTAMENTO,
			</if>
			<if test="fonoEmpleador1 != null">
				FONO_EMPLEADOR_1,
			</if>
			<if test="fonoCliente1 != null">
				FONO_CLIENTE_1,
			</if>
			<if test="fonoCliente2 != null">
				FONO_CLIENTE_2,
			</if>
			<if test="celular0 != null">
				CELULAR_0,
			</if>
			<if test="celular1 != null">
				CELULAR_1,
			</if>
			<if test="oficina != null">
				OFICINA,
			</if>
			<if test="casa != null">
				CASA,
			</if>
			<if test="cel1 != null">
				CEL1,
			</if>
			<if test="cel2 != null">
				CEL2,
			</if>
			<if test="cel3 != null">
				CEL3,
			</if>
			<if test="cel4 != null">
				CEL4,
			</if>
			<if test="cel5 != null">
				CEL5,
			</if>
			<if test="estado != null">
				ESTADO,
			</if>
			<if test="desMensaje != null">
				DES_MENSAJE,
			</if>
		</trim>
		<trim prefix="values (" suffix=")" suffixOverrides=",">
			<if test="codBase != null">
				#{codBase,jdbcType=NUMERIC},
			</if>
			<if test="secuenciaTlmk != null">
				#{secuenciaTlmk,jdbcType=NVARCHAR},
			</if>
			<if test="target != null">
				#{target,jdbcType=NVARCHAR},
			</if>
			<if test="fueMax != null">
				#{fueMax,jdbcType=NVARCHAR},
			</if>
			<if test="marca1 != null">
				#{marca1,jdbcType=NVARCHAR},
			</if>
			<if test="docideEnl != null">
				#{docideEnl,jdbcType=NVARCHAR},
			</if>
			<if test="tipdoc != null">
				#{tipdoc,jdbcType=NVARCHAR},
			</if>
			<if test="tipTarjeta != null">
				#{tipTarjeta,jdbcType=NVARCHAR},
			</if>
			<if test="rangoUtilizacion != null">
				#{rangoUtilizacion,jdbcType=NVARCHAR},
			</if>
			<if test="rangoLineaRipley != null">
				#{rangoLineaRipley,jdbcType=NVARCHAR},
			</if>
			<if test="rangoSaldosRipley != null">
				#{rangoSaldosRipley,jdbcType=NVARCHAR},
			</if>
			<if test="rangoAntiguedad != null">
				#{rangoAntiguedad,jdbcType=NVARCHAR},
			</if>
			<if test="recenciaTo != null">
				#{recenciaTo,jdbcType=NVARCHAR},
			</if>
			<if test="fechaAct != null">
				#{fechaAct,jdbcType=TIMESTAMP},
			</if>
			<if test="fechaVencimiento != null">
				#{fechaVencimiento,jdbcType=TIMESTAMP},
			</if>
			<if test="fechaEmbozado != null">
				#{fechaEmbozado,jdbcType=TIMESTAMP},
			</if>
			<if test="sexo != null">
				#{sexo,jdbcType=NVARCHAR},
			</if>
			<if test="edad != null">
				#{edad,jdbcType=NVARCHAR},
			</if>
			<if test="nse != null">
				#{nse,jdbcType=NVARCHAR},
			</if>
			<if test="nombresyapellidos != null">
				#{nombresyapellidos,jdbcType=NVARCHAR},
			</if>
			<if test="ocupacion != null">
				#{ocupacion,jdbcType=NVARCHAR},
			</if>
			<if test="direccion != null">
				#{direccion,jdbcType=NVARCHAR},
			</if>
			<if test="distrito != null">
				#{distrito,jdbcType=NVARCHAR},
			</if>
			<if test="departamento != null">
				#{departamento,jdbcType=NVARCHAR},
			</if>
			<if test="fonoEmpleador1 != null">
				#{fonoEmpleador1,jdbcType=NVARCHAR},
			</if>
			<if test="fonoCliente1 != null">
				#{fonoCliente1,jdbcType=NVARCHAR},
			</if>
			<if test="fonoCliente2 != null">
				#{fonoCliente2,jdbcType=NVARCHAR},
			</if>
			<if test="celular0 != null">
				#{celular0,jdbcType=NVARCHAR},
			</if>
			<if test="celular1 != null">
				#{celular1,jdbcType=NVARCHAR},
			</if>
			<if test="oficina != null">
				#{oficina,jdbcType=NVARCHAR},
			</if>
			<if test="casa != null">
				#{casa,jdbcType=NVARCHAR},
			</if>
			<if test="cel1 != null">
				#{cel1,jdbcType=NVARCHAR},
			</if>
			<if test="cel2 != null">
				#{cel2,jdbcType=NVARCHAR},
			</if>
			<if test="cel3 != null">
				#{cel3,jdbcType=NVARCHAR},
			</if>
			<if test="cel4 != null">
				#{cel4,jdbcType=NVARCHAR},
			</if>
			<if test="cel5 != null">
				#{cel5,jdbcType=NVARCHAR},
			</if>
			<if test="estado != null">
				#{estado,jdbcType=NVARCHAR},
			</if>
			<if test="desMensaje != null">
				#{desMensaje,jdbcType=NVARCHAR},
			</if>
		</trim>
	</insert>
	<select id="countByExample" parameterType="com.cardif.satelite.model.TlmkBaseRPExample" resultType="java.lang.Integer">
		<!-- WARNING - @mbggenerated This element is automatically generated by MyBatis Generator, do not modify. This element was generated on Wed Jan 22 12:45:18 
			COT 2014. -->
		select count(*) from dbo.TLMK_BASE_RP
		<if test="_parameter != null">
			<include refid="Example_Where_Clause" />
		</if>
	</select>
	<update id="updateByExampleSelective" parameterType="map">
		<!-- WARNING - @mbggenerated This element is automatically generated by MyBatis Generator, do not modify. This element was generated on Wed Jan 22 12:45:18 
			COT 2014. -->
		update dbo.TLMK_BASE_RP
		<set>
			<if test="record.pk != null">
				PK = #{record.pk,jdbcType=NUMERIC},
			</if>
			<if test="record.codBase != null">
				COD_BASE = #{record.codBase,jdbcType=NUMERIC},
			</if>
			<if test="record.secuenciaTlmk != null">
				SECUENCIA_TLMK = #{record.secuenciaTlmk,jdbcType=NVARCHAR},
			</if>
			<if test="record.target != null">
				TARGET = #{record.target,jdbcType=NVARCHAR},
			</if>
			<if test="record.fueMax != null">
				FUE_MAX = #{record.fueMax,jdbcType=NVARCHAR},
			</if>
			<if test="record.marca1 != null">
				MARCA1 = #{record.marca1,jdbcType=NVARCHAR},
			</if>
			<if test="record.docideEnl != null">
				DOCIDE_ENL = #{record.docideEnl,jdbcType=NVARCHAR},
			</if>
			<if test="record.tipdoc != null">
				TIPDOC = #{record.tipdoc,jdbcType=NVARCHAR},
			</if>
			<if test="record.tipTarjeta != null">
				TIP_TARJETA = #{record.tipTarjeta,jdbcType=NVARCHAR},
			</if>
			<if test="record.rangoUtilizacion != null">
				RANGO_UTILIZACION = #{record.rangoUtilizacion,jdbcType=NVARCHAR},
			</if>
			<if test="record.rangoLineaRipley != null">
				RANGO_LINEA_RIPLEY = #{record.rangoLineaRipley,jdbcType=NVARCHAR},
			</if>
			<if test="record.rangoSaldosRipley != null">
				RANGO_SALDOS_RIPLEY = #{record.rangoSaldosRipley,jdbcType=NVARCHAR},
			</if>
			<if test="record.rangoAntiguedad != null">
				RANGO_ANTIGUEDAD = #{record.rangoAntiguedad,jdbcType=NVARCHAR},
			</if>
			<if test="record.recenciaTo != null">
				RECENCIA_TO = #{record.recenciaTo,jdbcType=NVARCHAR},
			</if>
			<if test="record.fechaAct != null">
				FECHA_ACT = #{record.fechaAct,jdbcType=TIMESTAMP},
			</if>
			<if test="record.fechaVencimiento != null">
				FECHA_VENCIMIENTO = #{record.fechaVencimiento,jdbcType=TIMESTAMP},
			</if>
			<if test="record.fechaEmbozado != null">
				FECHA_EMBOZADO = #{record.fechaEmbozado,jdbcType=TIMESTAMP},
			</if>
			<if test="record.sexo != null">
				SEXO = #{record.sexo,jdbcType=NVARCHAR},
			</if>
			<if test="record.edad != null">
				EDAD = #{record.edad,jdbcType=NVARCHAR},
			</if>
			<if test="record.nse != null">
				NSE = #{record.nse,jdbcType=NVARCHAR},
			</if>
			<if test="record.nombresyapellidos != null">
				NOMBRESYAPELLIDOS = #{record.nombresyapellidos,jdbcType=NVARCHAR},
			</if>
			<if test="record.ocupacion != null">
				OCUPACION = #{record.ocupacion,jdbcType=NVARCHAR},
			</if>
			<if test="record.direccion != null">
				DIRECCION = #{record.direccion,jdbcType=NVARCHAR},
			</if>
			<if test="record.distrito != null">
				DISTRITO = #{record.distrito,jdbcType=NVARCHAR},
			</if>
			<if test="record.departamento != null">
				DEPARTAMENTO = #{record.departamento,jdbcType=NVARCHAR},
			</if>
			<if test="record.fonoEmpleador1 != null">
				FONO_EMPLEADOR_1 = #{record.fonoEmpleador1,jdbcType=NVARCHAR},
			</if>
			<if test="record.fonoCliente1 != null">
				FONO_CLIENTE_1 = #{record.fonoCliente1,jdbcType=NVARCHAR},
			</if>
			<if test="record.fonoCliente2 != null">
				FONO_CLIENTE_2 = #{record.fonoCliente2,jdbcType=NVARCHAR},
			</if>
			<if test="record.celular0 != null">
				CELULAR_0 = #{record.celular0,jdbcType=NVARCHAR},
			</if>
			<if test="record.celular1 != null">
				CELULAR_1 = #{record.celular1,jdbcType=NVARCHAR},
			</if>
			<if test="record.oficina != null">
				OFICINA = #{record.oficina,jdbcType=NVARCHAR},
			</if>
			<if test="record.casa != null">
				CASA = #{record.casa,jdbcType=NVARCHAR},
			</if>
			<if test="record.cel1 != null">
				CEL1 = #{record.cel1,jdbcType=NVARCHAR},
			</if>
			<if test="record.cel2 != null">
				CEL2 = #{record.cel2,jdbcType=NVARCHAR},
			</if>
			<if test="record.cel3 != null">
				CEL3 = #{record.cel3,jdbcType=NVARCHAR},
			</if>
			<if test="record.cel4 != null">
				CEL4 = #{record.cel4,jdbcType=NVARCHAR},
			</if>
			<if test="record.cel5 != null">
				CEL5 = #{record.cel5,jdbcType=NVARCHAR},
			</if>
			<if test="record.estado != null">
				ESTADO = #{record.estado,jdbcType=NVARCHAR},
			</if>
			<if test="record.desMensaje != null">
				DES_MENSAJE = #{record.desMensaje,jdbcType=NVARCHAR},
			</if>
		</set>
		<if test="_parameter != null">
			<include refid="Update_By_Example_Where_Clause" />
		</if>
	</update>
	<update id="updateByExample" parameterType="map">
		<!-- WARNING - @mbggenerated This element is automatically generated by MyBatis Generator, do not modify. This element was generated on Wed Jan 22 12:45:18 
			COT 2014. -->
		update dbo.TLMK_BASE_RP
		set PK = #{record.pk,jdbcType=NUMERIC},
		COD_BASE = #{record.codBase,jdbcType=NUMERIC},
		SECUENCIA_TLMK =
		#{record.secuenciaTlmk,jdbcType=NVARCHAR},
		TARGET = #{record.target,jdbcType=NVARCHAR},
		FUE_MAX = #{record.fueMax,jdbcType=NVARCHAR},
		MARCA1 =
		#{record.marca1,jdbcType=NVARCHAR},
		DOCIDE_ENL = #{record.docideEnl,jdbcType=NVARCHAR},
		TIPDOC = #{record.tipdoc,jdbcType=NVARCHAR},
		TIP_TARJETA =
		#{record.tipTarjeta,jdbcType=NVARCHAR},
		RANGO_UTILIZACION = #{record.rangoUtilizacion,jdbcType=NVARCHAR},
		RANGO_LINEA_RIPLEY =
		#{record.rangoLineaRipley,jdbcType=NVARCHAR},
		RANGO_SALDOS_RIPLEY = #{record.rangoSaldosRipley,jdbcType=NVARCHAR},
		RANGO_ANTIGUEDAD =
		#{record.rangoAntiguedad,jdbcType=NVARCHAR},
		RECENCIA_TO = #{record.recenciaTo,jdbcType=NVARCHAR},
		FECHA_ACT = #{record.fechaAct,jdbcType=TIMESTAMP},
		FECHA_VENCIMIENTO = #{record.fechaVencimiento,jdbcType=TIMESTAMP},
		FECHA_EMBOZADO = #{record.fechaEmbozado,jdbcType=TIMESTAMP},
		SEXO =
		#{record.sexo,jdbcType=NVARCHAR},
		EDAD = #{record.edad,jdbcType=NVARCHAR},
		NSE = #{record.nse,jdbcType=NVARCHAR},
		NOMBRESYAPELLIDOS =
		#{record.nombresyapellidos,jdbcType=NVARCHAR},
		OCUPACION = #{record.ocupacion,jdbcType=NVARCHAR},
		DIRECCION = #{record.direccion,jdbcType=NVARCHAR},
		DISTRITO = #{record.distrito,jdbcType=NVARCHAR},
		DEPARTAMENTO = #{record.departamento,jdbcType=NVARCHAR},
		FONO_EMPLEADOR_1 =
		#{record.fonoEmpleador1,jdbcType=NVARCHAR},
		FONO_CLIENTE_1 = #{record.fonoCliente1,jdbcType=NVARCHAR},
		FONO_CLIENTE_2 =
		#{record.fonoCliente2,jdbcType=NVARCHAR},
		CELULAR_0 = #{record.celular0,jdbcType=NVARCHAR},
		CELULAR_1 = #{record.celular1,jdbcType=NVARCHAR},
		OFICINA =
		#{record.oficina,jdbcType=NVARCHAR},
		CASA = #{record.casa,jdbcType=NVARCHAR},
		CEL1 = #{record.cel1,jdbcType=NVARCHAR},
		CEL2 =
		#{record.cel2,jdbcType=NVARCHAR},
		CEL3 = #{record.cel3,jdbcType=NVARCHAR},
		CEL4 = #{record.cel4,jdbcType=NVARCHAR},
		CEL5 =
		#{record.cel5,jdbcType=NVARCHAR},
		ESTADO = #{record.estado,jdbcType=NVARCHAR},
		DES_MENSAJE = #{record.desMensaje,jdbcType=NVARCHAR}
		<if test="_parameter != null">
			<include refid="Update_By_Example_Where_Clause" />
		</if>
	</update>
	<update id="updateByPrimaryKeySelective" parameterType="com.cardif.satelite.model.TlmkBaseRP">
		<!-- WARNING - @mbggenerated This element is automatically generated by MyBatis Generator, do not modify. This element was generated on Wed Jan 22 12:45:18 
			COT 2014. -->
		update dbo.TLMK_BASE_RP
		<set>
			<if test="codBase != null">
				COD_BASE = #{codBase,jdbcType=NUMERIC},
			</if>
			<if test="secuenciaTlmk != null">
				SECUENCIA_TLMK = #{secuenciaTlmk,jdbcType=NVARCHAR},
			</if>
			<if test="target != null">
				TARGET = #{target,jdbcType=NVARCHAR},
			</if>
			<if test="fueMax != null">
				FUE_MAX = #{fueMax,jdbcType=NVARCHAR},
			</if>
			<if test="marca1 != null">
				MARCA1 = #{marca1,jdbcType=NVARCHAR},
			</if>
			<if test="docideEnl != null">
				DOCIDE_ENL = #{docideEnl,jdbcType=NVARCHAR},
			</if>
			<if test="tipdoc != null">
				TIPDOC = #{tipdoc,jdbcType=NVARCHAR},
			</if>
			<if test="tipTarjeta != null">
				TIP_TARJETA = #{tipTarjeta,jdbcType=NVARCHAR},
			</if>
			<if test="rangoUtilizacion != null">
				RANGO_UTILIZACION = #{rangoUtilizacion,jdbcType=NVARCHAR},
			</if>
			<if test="rangoLineaRipley != null">
				RANGO_LINEA_RIPLEY = #{rangoLineaRipley,jdbcType=NVARCHAR},
			</if>
			<if test="rangoSaldosRipley != null">
				RANGO_SALDOS_RIPLEY = #{rangoSaldosRipley,jdbcType=NVARCHAR},
			</if>
			<if test="rangoAntiguedad != null">
				RANGO_ANTIGUEDAD = #{rangoAntiguedad,jdbcType=NVARCHAR},
			</if>
			<if test="recenciaTo != null">
				RECENCIA_TO = #{recenciaTo,jdbcType=NVARCHAR},
			</if>
			<if test="fechaAct != null">
				FECHA_ACT = #{fechaAct,jdbcType=TIMESTAMP},
			</if>
			<if test="fechaVencimiento != null">
				FECHA_VENCIMIENTO = #{fechaVencimiento,jdbcType=TIMESTAMP},
			</if>
			<if test="fechaEmbozado != null">
				FECHA_EMBOZADO = #{fechaEmbozado,jdbcType=TIMESTAMP},
			</if>
			<if test="sexo != null">
				SEXO = #{sexo,jdbcType=NVARCHAR},
			</if>
			<if test="edad != null">
				EDAD = #{edad,jdbcType=NVARCHAR},
			</if>
			<if test="nse != null">
				NSE = #{nse,jdbcType=NVARCHAR},
			</if>
			<if test="nombresyapellidos != null">
				NOMBRESYAPELLIDOS = #{nombresyapellidos,jdbcType=NVARCHAR},
			</if>
			<if test="ocupacion != null">
				OCUPACION = #{ocupacion,jdbcType=NVARCHAR},
			</if>
			<if test="direccion != null">
				DIRECCION = #{direccion,jdbcType=NVARCHAR},
			</if>
			<if test="distrito != null">
				DISTRITO = #{distrito,jdbcType=NVARCHAR},
			</if>
			<if test="departamento != null">
				DEPARTAMENTO = #{departamento,jdbcType=NVARCHAR},
			</if>
			<if test="fonoEmpleador1 != null">
				FONO_EMPLEADOR_1 = #{fonoEmpleador1,jdbcType=NVARCHAR},
			</if>
			<if test="fonoCliente1 != null">
				FONO_CLIENTE_1 = #{fonoCliente1,jdbcType=NVARCHAR},
			</if>
			<if test="fonoCliente2 != null">
				FONO_CLIENTE_2 = #{fonoCliente2,jdbcType=NVARCHAR},
			</if>
			<if test="celular0 != null">
				CELULAR_0 = #{celular0,jdbcType=NVARCHAR},
			</if>
			<if test="celular1 != null">
				CELULAR_1 = #{celular1,jdbcType=NVARCHAR},
			</if>
			<if test="oficina != null">
				OFICINA = #{oficina,jdbcType=NVARCHAR},
			</if>
			<if test="casa != null">
				CASA = #{casa,jdbcType=NVARCHAR},
			</if>
			<if test="cel1 != null">
				CEL1 = #{cel1,jdbcType=NVARCHAR},
			</if>
			<if test="cel2 != null">
				CEL2 = #{cel2,jdbcType=NVARCHAR},
			</if>
			<if test="cel3 != null">
				CEL3 = #{cel3,jdbcType=NVARCHAR},
			</if>
			<if test="cel4 != null">
				CEL4 = #{cel4,jdbcType=NVARCHAR},
			</if>
			<if test="cel5 != null">
				CEL5 = #{cel5,jdbcType=NVARCHAR},
			</if>
			<if test="estado != null">
				ESTADO = #{estado,jdbcType=NVARCHAR},
			</if>
			<if test="desMensaje != null">
				DES_MENSAJE = #{desMensaje,jdbcType=NVARCHAR},
			</if>
		</set>
		where PK = #{pk,jdbcType=NUMERIC}
	</update>
	<update id="updateByPrimaryKey" parameterType="com.cardif.satelite.model.TlmkBaseRP">
		<!-- WARNING - @mbggenerated This element is automatically generated by MyBatis Generator, do not modify. This element was generated on Wed Jan 22 12:45:18 
			COT 2014. -->
		update dbo.TLMK_BASE_RP
		set COD_BASE = #{codBase,jdbcType=NUMERIC},
		SECUENCIA_TLMK = #{secuenciaTlmk,jdbcType=NVARCHAR},
		TARGET =
		#{target,jdbcType=NVARCHAR},
		FUE_MAX = #{fueMax,jdbcType=NVARCHAR},
		MARCA1 = #{marca1,jdbcType=NVARCHAR},
		DOCIDE_ENL = #{docideEnl,jdbcType=NVARCHAR},
		TIPDOC = #{tipdoc,jdbcType=NVARCHAR},
		TIP_TARJETA = #{tipTarjeta,jdbcType=NVARCHAR},
		RANGO_UTILIZACION = #{rangoUtilizacion,jdbcType=NVARCHAR},
		RANGO_LINEA_RIPLEY = #{rangoLineaRipley,jdbcType=NVARCHAR},
		RANGO_SALDOS_RIPLEY = #{rangoSaldosRipley,jdbcType=NVARCHAR},
		RANGO_ANTIGUEDAD =
		#{rangoAntiguedad,jdbcType=NVARCHAR},
		RECENCIA_TO = #{recenciaTo,jdbcType=NVARCHAR},
		FECHA_ACT = #{fechaAct,jdbcType=TIMESTAMP},
		FECHA_VENCIMIENTO =
		#{fechaVencimiento,jdbcType=TIMESTAMP},
		FECHA_EMBOZADO = #{fechaEmbozado,jdbcType=TIMESTAMP},
		SEXO = #{sexo,jdbcType=NVARCHAR},
		EDAD =
		#{edad,jdbcType=NVARCHAR},
		NSE = #{nse,jdbcType=NVARCHAR},
		NOMBRESYAPELLIDOS = #{nombresyapellidos,jdbcType=NVARCHAR},
		OCUPACION =
		#{ocupacion,jdbcType=NVARCHAR},
		DIRECCION = #{direccion,jdbcType=NVARCHAR},
		DISTRITO = #{distrito,jdbcType=NVARCHAR},
		DEPARTAMENTO =
		#{departamento,jdbcType=NVARCHAR},
		FONO_EMPLEADOR_1 = #{fonoEmpleador1,jdbcType=NVARCHAR},
		FONO_CLIENTE_1 = #{fonoCliente1,jdbcType=NVARCHAR},
		FONO_CLIENTE_2 = #{fonoCliente2,jdbcType=NVARCHAR},
		CELULAR_0 = #{celular0,jdbcType=NVARCHAR},
		CELULAR_1 = #{celular1,jdbcType=NVARCHAR},
		OFICINA =
		#{oficina,jdbcType=NVARCHAR},
		CASA = #{casa,jdbcType=NVARCHAR},
		CEL1 = #{cel1,jdbcType=NVARCHAR},
		CEL2 = #{cel2,jdbcType=NVARCHAR},
		CEL3 =
		#{cel3,jdbcType=NVARCHAR},
		CEL4 = #{cel4,jdbcType=NVARCHAR},
		CEL5 = #{cel5,jdbcType=NVARCHAR},
		ESTADO = #{estado,jdbcType=NVARCHAR},
		DES_MENSAJE =
		#{desMensaje,jdbcType=NVARCHAR}
		where PK = #{pk,jdbcType=NUMERIC}
	</update>
</mapper>